AUTHORS
ChangeLog
LICENSE
MANIFEST.in
README
ez_setup.py
setup.cfg
setup.py
python_sbigudrv.egg-info/PKG-INFO
python_sbigudrv.egg-info/SOURCES.txt
python_sbigudrv.egg-info/dependency_links.txt
python_sbigudrv.egg-info/not-zip-safe
python_sbigudrv.egg-info/top_level.txt
sbigudrv/__init__.py
sbigudrv/libsbigudrv-4.57-linux-amd32.a
sbigudrv/libsbigudrv-4.57-linux-amd64.a
sbigudrv/numpy.i
sbigudrv/sbigudrv.h
sbigudrv/sbigudrv.i
sbigudrv/sbigudrv.py
sbigudrv/sbigudrv_wrap.c