Metadata-Version: 1.0
Name: python-sbigudrv
Version: 0.5
Summary: Python wrappers for SBIG (tm) Universal Driver
Home-page: http://code.google.com/p/python-sbigudrv
Author: Paulo Henrique Silva
Author-email: ph.silva@gmail.com
License: Apache License 2.0
Platform: UNKNOWN
Classifier: Development Status :: 4 - Beta
Classifier: Environment :: Console
Classifier: Intended Audience :: Science/Research
Classifier: Intended Audience :: Developers
Classifier: License :: OSI Approved :: Apache Software License
Classifier: Natural Language :: English
Classifier: Operating System :: POSIX :: Linux
Classifier: Programming Language :: Python
Classifier: Topic :: Scientific/Engineering :: Astronomy
Classifier: Topic :: Software Development :: Libraries :: Python Modules
